sp_ask_chats_utils/__init__.py
sp_ask_chats_utils-0.1.2.dist-info/WHEEL
sp_ask_chats_utils-0.1.2.dist-info/METADATA
sp_ask_chats_utils-0.1.2.dist-info/RECORD
