Metadata-Version: 2.1
Name: sp-ask-chats-utils
Version: 0.1.2
Summary: 
Home-page: https://github.com/guinslym/sp_ask_chats_utils
License: MIT
Keywords: Ask,Scholars Portal,Ontario,Chats
Author: Guinsly Mondesir
Author-email: guinslym@gmail.com
Requires-Python: >=3.7,<4.0
Classifier: License :: OSI Approved :: MIT License
Classifier: Operating System :: OS Independent
Classifier: Programming Language :: Python :: 3
Classifier: Programming Language :: Python :: 3.7
Classifier: Programming Language :: Python :: 3.8
Classifier: Topic :: Software Development :: Documentation
Classifier: Topic :: Software Development :: Libraries :: Python Modules
Classifier: Topic :: Software Development :: Quality Assurance
Project-URL: Repository, https://github.com/guinslym/sp_ask_chats_utils
